{"dependencies":[{"name":"/home/misha/Documents/Projects/honeymate/package.json","includedInParent":true,"mtime":1529431010290},{"name":"./generateEffect","loc":{"line":1,"column":27},"parent":"/home/misha/Documents/Projects/honeymate/source/node.js","resolved":"/home/misha/Documents/Projects/honeymate/source/generateEffect.js"},{"name":"./wait","loc":{"line":2,"column":23},"parent":"/home/misha/Documents/Projects/honeymate/source/node.js","resolved":"/home/misha/Documents/Projects/honeymate/source/wait.js"}],"generated":{"js":"'use strict';\n\nObject.defineProperty(exports, \"__esModule\", {\n    value: true\n});\n\nvar _createClass = function () { function defineProperties(target, props) { for (var i = 0; i < props.length; i++) { var descriptor = props[i]; descriptor.enumerable = descriptor.enumerable || false; descriptor.configurable = true; if (\"value\" in descriptor) descriptor.writable = true; Object.defineProperty(target, descriptor.key, descriptor); } } return function (Constructor, protoProps, staticProps) { if (protoProps) defineProperties(Constructor.prototype, protoProps); if (staticProps) defineProperties(Constructor, staticProps); return Constructor; }; }();\n\nvar _generateEffect = require('./generateEffect');\n\nvar _generateEffect2 = _interopRequireDefault(_generateEffect);\n\nvar _wait = require('./wait');\n\nvar _wait2 = _interopRequireDefault(_wait);\n\nfunction _interopRequireDefault(obj) { return obj && obj.__esModule ? obj : { default: obj }; }\n\nfunction _asyncToGenerator(fn) { return function () { var gen = fn.apply(this, arguments); return new Promise(function (resolve, reject) { function step(key, arg) { try { var info = gen[key](arg); var value = info.value; } catch (error) { reject(error); return; } if (info.done) { resolve(value); } else { return Promise.resolve(value).then(function (value) { step(\"next\", value); }, function (err) { step(\"throw\", err); }); } } return step(\"next\"); }); }; }\n\nfunction _classCallCheck(instance, Constructor) { if (!(instance instanceof Constructor)) { throw new TypeError(\"Cannot call a class as a function\"); } }\n\nvar getDirection = function getDirection(dataset) {\n    if (dataset.right) {\n        return 2;\n    } else if (dataset.down) {\n        return 3;\n    } else if (dataset.left) {\n        return 4;\n    } else {\n        return 1;\n    }\n};\n\nvar parseParameters = function parseParameters(dataset) {\n    return {\n        direction: getDirection(dataset),\n        duration: dataset.duration ? dataset.duration : 640,\n        effect: dataset.effect ? dataset.effect : 'fade',\n        expose: dataset.expose ? dataset.expose === 'true' : false,\n        delay: dataset.delay ? parseInt(dataset.delay, 10) : 0,\n        hold: dataset.hold ? parseInt(dataset.hold, 10) : 0,\n        scale: dataset.scale ? dataset.scale : 0.87,\n        await: dataset.await ? dataset.await : null,\n        'continue': dataset.continue === 'true',\n        origin: dataset.origin ? dataset.origin : 'bottom',\n        offset: dataset.up || dataset.down || dataset.left || dataset.right ? dataset.up || dataset.down || dataset.left || dataset.right : 32\n    };\n};\n\nvar HoneyNode = function () {\n    function HoneyNode(node) {\n        _classCallCheck(this, HoneyNode);\n\n        node.style.opacity = 0;\n        this.node = node;\n        this.setParameters(node.dataset);\n    }\n\n    _createClass(HoneyNode, [{\n        key: 'setParameters',\n        value: function setParameters(parameters) {\n            this.parameters = parseParameters(parameters);\n            this.effect = (0, _generateEffect2.default)(this.parameters);\n        }\n    }, {\n        key: 'applyEffect',\n        value: function () {\n            var _ref = _asyncToGenerator( /*#__PURE__*/regeneratorRuntime.mark(function _callee(effect) {\n                var _this = this;\n\n                var count;\n                return regeneratorRuntime.wrap(function _callee$(_context) {\n                    while (1) {\n                        switch (_context.prev = _context.next) {\n                            case 0:\n                                count = 0;\n\n                                Object.keys(effect).forEach(function (key) {\n                                    _this.node.style[key] = effect[key];\n                                    count++;\n                                });\n                                return _context.abrupt('return', count);\n\n                            case 3:\n                            case 'end':\n                                return _context.stop();\n                        }\n                    }\n                }, _callee, this);\n            }));\n\n            function applyEffect(_x) {\n                return _ref.apply(this, arguments);\n            }\n\n            return applyEffect;\n        }()\n    }, {\n        key: 'isLoaded',\n        value: function () {\n            var _ref2 = _asyncToGenerator( /*#__PURE__*/regeneratorRuntime.mark(function _callee2() {\n                var _this2 = this;\n\n                return regeneratorRuntime.wrap(function _callee2$(_context2) {\n                    while (1) {\n                        switch (_context2.prev = _context2.next) {\n                            case 0:\n                                return _context2.abrupt('return', new Promise(function (resolve) {\n                                    (0, _wait2.default)(_this2.node).then(function () {\n                                        return setTimeout(function () {\n                                            return resolve();\n                                        }, _this2.parameters.hold);\n                                    });\n                                }));\n\n                            case 1:\n                            case 'end':\n                                return _context2.stop();\n                        }\n                    }\n                }, _callee2, this);\n            }));\n\n            function isLoaded() {\n                return _ref2.apply(this, arguments);\n            }\n\n            return isLoaded;\n        }()\n    }, {\n        key: 'animate',\n        value: function animate() {\n            var _this3 = this;\n\n            var effect = arguments.length > 0 && arguments[0] !== undefined ? arguments[0] : this.effect;\n\n            this.applyEffect(effect).then(function () {\n                _this3.isLoaded().then(function () {\n                    setTimeout(function () {\n                        _this3.expose();\n                    }, _this3.parameters.delay);\n                });\n            });\n        }\n    }, {\n        key: 'expose',\n        value: function expose() {\n            this.applyEffect({\n                transform: '',\n                opacity: 1\n            });\n        }\n    }]);\n\n    return HoneyNode;\n}();\n\nexports.default = HoneyNode;","map":{"mappings":[{"generated":{"line":9,"column":0},"source":"node.js","original":{"line":1,"column":0}},{"generated":{"line":13,"column":0},"source":"node.js","original":{"line":2,"column":0}},{"generated":{"line":23,"column":0},"source":"node.js","original":{"line":4,"column":0}},{"name":"getDirection","generated":{"line":23,"column":4},"source":"node.js","original":{"line":4,"column":6}},{"generated":{"line":23,"column":19},"source":"node.js","original":{"line":4,"column":21}},{"name":"getDirection","generated":{"line":23,"column":28},"source":"node.js","original":{"line":4,"column":6}},{"generated":{"line":23,"column":40},"source":"node.js","original":{"line":4,"column":21}},{"name":"dataset","generated":{"line":23,"column":41},"source":"node.js","original":{"line":4,"column":22}},{"generated":{"line":23,"column":48},"source":"node.js","original":{"line":4,"column":21}},{"generated":{"line":23,"column":50},"source":"node.js","original":{"line":4,"column":34}},{"generated":{"line":24,"column":0},"source":"node.js","original":{"line":5,"column":4}},{"name":"dataset","generated":{"line":24,"column":8},"source":"node.js","original":{"line":5,"column":8}},{"name":"right","generated":{"line":24,"column":16},"source":"node.js","original":{"line":5,"column":16}},{"generated":{"line":24,"column":21},"source":"node.js","original":{"line":5,"column":4}},{"generated":{"line":24,"column":23},"source":"node.js","original":{"line":5,"column":23}},{"generated":{"line":25,"column":0},"source":"node.js","original":{"line":6,"column":8}},{"generated":{"line":25,"column":15},"source":"node.js","original":{"line":6,"column":15}},{"generated":{"line":25,"column":16},"source":"node.js","original":{"line":6,"column":8}},{"generated":{"line":26,"column":0},"source":"node.js","original":{"line":7,"column":5}},{"generated":{"line":26,"column":5},"source":"node.js","original":{"line":5,"column":4}},{"generated":{"line":26,"column":11},"source":"node.js","original":{"line":7,"column":11}},{"name":"dataset","generated":{"line":26,"column":15},"source":"node.js","original":{"line":7,"column":15}},{"name":"down","generated":{"line":26,"column":23},"source":"node.js","original":{"line":7,"column":23}},{"generated":{"line":26,"column":27},"source":"node.js","original":{"line":7,"column":11}},{"generated":{"line":26,"column":29},"source":"node.js","original":{"line":7,"column":29}},{"generated":{"line":27,"column":0},"source":"node.js","original":{"line":8,"column":8}},{"generated":{"line":27,"column":15},"source":"node.js","original":{"line":8,"column":15}},{"generated":{"line":27,"column":16},"source":"node.js","original":{"line":8,"column":8}},{"generated":{"line":28,"column":0},"source":"node.js","original":{"line":9,"column":5}},{"generated":{"line":28,"column":5},"source":"node.js","original":{"line":7,"column":11}},{"generated":{"line":28,"column":11},"source":"node.js","original":{"line":9,"column":11}},{"name":"dataset","generated":{"line":28,"column":15},"source":"node.js","original":{"line":9,"column":15}},{"name":"left","generated":{"line":28,"column":23},"source":"node.js","original":{"line":9,"column":23}},{"generated":{"line":28,"column":27},"source":"node.js","original":{"line":9,"column":11}},{"generated":{"line":28,"column":29},"source":"node.js","original":{"line":9,"column":29}},{"generated":{"line":29,"column":0},"source":"node.js","original":{"line":10,"column":8}},{"generated":{"line":29,"column":15},"source":"node.js","original":{"line":10,"column":15}},{"generated":{"line":29,"column":16},"source":"node.js","original":{"line":10,"column":8}},{"generated":{"line":30,"column":0},"source":"node.js","original":{"line":11,"column":5}},{"generated":{"line":30,"column":5},"source":"node.js","original":{"line":9,"column":11}},{"generated":{"line":30,"column":11},"source":"node.js","original":{"line":11,"column":11}},{"generated":{"line":31,"column":0},"source":"node.js","original":{"line":12,"column":8}},{"generated":{"line":31,"column":15},"source":"node.js","original":{"line":12,"column":15}},{"generated":{"line":31,"column":16},"source":"node.js","original":{"line":12,"column":8}},{"generated":{"line":32,"column":0},"source":"node.js","original":{"line":13,"column":5}},{"generated":{"line":33,"column":0},"source":"node.js","original":{"line":14,"column":1}},{"generated":{"line":33,"column":1},"source":"node.js","original":{"line":4,"column":0}},{"generated":{"line":35,"column":0},"source":"node.js","original":{"line":16,"column":0}},{"name":"parseParameters","generated":{"line":35,"column":4},"source":"node.js","original":{"line":16,"column":6}},{"generated":{"line":35,"column":22},"source":"node.js","original":{"line":16,"column":24}},{"name":"parseParameters","generated":{"line":35,"column":31},"source":"node.js","original":{"line":16,"column":6}},{"generated":{"line":35,"column":46},"source":"node.js","original":{"line":16,"column":24}},{"name":"dataset","generated":{"line":35,"column":47},"source":"node.js","original":{"line":16,"column":25}},{"generated":{"line":35,"column":54},"source":"node.js","original":{"line":16,"column":24}},{"generated":{"line":35,"column":56},"source":"node.js","original":{"line":16,"column":37}},{"generated":{"line":36,"column":0},"source":"node.js","original":{"line":17,"column":4}},{"generated":{"line":36,"column":11},"source":"node.js","original":{"line":17,"column":11}},{"name":"direction","generated":{"line":37,"column":0},"source":"node.js","original":{"line":18,"column":8}},{"name":"getDirection","generated":{"line":37,"column":19},"source":"node.js","original":{"line":18,"column":19}},{"name":"dataset","generated":{"line":37,"column":32},"source":"node.js","original":{"line":18,"column":32}},{"generated":{"line":37,"column":39},"source":"node.js","original":{"line":18,"column":19}},{"generated":{"line":37,"column":40},"source":"node.js","original":{"line":17,"column":11}},{"name":"duration","generated":{"line":38,"column":0},"source":"node.js","original":{"line":19,"column":8}},{"name":"dataset","generated":{"line":38,"column":18},"source":"node.js","original":{"line":19,"column":18}},{"name":"duration","generated":{"line":38,"column":26},"source":"node.js","original":{"line":19,"column":26}},{"generated":{"line":38,"column":34},"source":"node.js","original":{"line":19,"column":18}},{"name":"dataset","generated":{"line":38,"column":37},"source":"node.js","original":{"line":19,"column":37}},{"name":"duration","generated":{"line":38,"column":45},"source":"node.js","original":{"line":19,"column":45}},{"generated":{"line":38,"column":53},"source":"node.js","original":{"line":19,"column":18}},{"generated":{"line":38,"column":56},"source":"node.js","original":{"line":19,"column":56}},{"generated":{"line":38,"column":59},"source":"node.js","original":{"line":17,"column":11}},{"name":"effect","generated":{"line":39,"column":0},"source":"node.js","original":{"line":20,"column":8}},{"name":"dataset","generated":{"line":39,"column":16},"source":"node.js","original":{"line":20,"column":16}},{"name":"effect","generated":{"line":39,"column":24},"source":"node.js","original":{"line":20,"column":24}},{"generated":{"line":39,"column":30},"source":"node.js","original":{"line":20,"column":16}},{"name":"dataset","generated":{"line":39,"column":33},"source":"node.js","original":{"line":20,"column":33}},{"name":"effect","generated":{"line":39,"column":41},"source":"node.js","original":{"line":20,"column":41}},{"generated":{"line":39,"column":47},"source":"node.js","original":{"line":20,"column":16}},{"generated":{"line":39,"column":50},"source":"node.js","original":{"line":20,"column":50}},{"generated":{"line":39,"column":56},"source":"node.js","original":{"line":17,"column":11}},{"name":"expose","generated":{"line":40,"column":0},"source":"node.js","original":{"line":21,"column":8}},{"name":"dataset","generated":{"line":40,"column":16},"source":"node.js","original":{"line":21,"column":16}},{"name":"expose","generated":{"line":40,"column":24},"source":"node.js","original":{"line":21,"column":24}},{"generated":{"line":40,"column":30},"source":"node.js","original":{"line":21,"column":16}},{"name":"dataset","generated":{"line":40,"column":33},"source":"node.js","original":{"line":21,"column":33}},{"name":"expose","generated":{"line":40,"column":41},"source":"node.js","original":{"line":21,"column":41}},{"generated":{"line":40,"column":47},"source":"node.js","original":{"line":21,"column":33}},{"generated":{"line":40,"column":52},"source":"node.js","original":{"line":21,"column":52}},{"generated":{"line":40,"column":58},"source":"node.js","original":{"line":21,"column":16}},{"generated":{"line":40,"column":61},"source":"node.js","original":{"line":21,"column":61}},{"generated":{"line":40,"column":66},"source":"node.js","original":{"line":17,"column":11}},{"name":"delay","generated":{"line":41,"column":0},"source":"node.js","original":{"line":22,"column":8}},{"name":"dataset","generated":{"line":41,"column":15},"source":"node.js","original":{"line":22,"column":15}},{"name":"delay","generated":{"line":41,"column":23},"source":"node.js","original":{"line":22,"column":23}},{"generated":{"line":41,"column":28},"source":"node.js","original":{"line":22,"column":15}},{"name":"parseInt","generated":{"line":41,"column":31},"source":"node.js","original":{"line":22,"column":31}},{"name":"dataset","generated":{"line":41,"column":40},"source":"node.js","original":{"line":22,"column":40}},{"name":"delay","generated":{"line":41,"column":48},"source":"node.js","original":{"line":22,"column":48}},{"generated":{"line":41,"column":53},"source":"node.js","original":{"line":22,"column":31}},{"generated":{"line":41,"column":55},"source":"node.js","original":{"line":22,"column":55}},{"generated":{"line":41,"column":57},"source":"node.js","original":{"line":22,"column":31}},{"generated":{"line":41,"column":58},"source":"node.js","original":{"line":22,"column":15}},{"generated":{"line":41,"column":61},"source":"node.js","original":{"line":22,"column":61}},{"generated":{"line":41,"column":62},"source":"node.js","original":{"line":17,"column":11}},{"name":"hold","generated":{"line":42,"column":0},"source":"node.js","original":{"line":23,"column":8}},{"name":"dataset","generated":{"line":42,"column":14},"source":"node.js","original":{"line":23,"column":14}},{"name":"hold","generated":{"line":42,"column":22},"source":"node.js","original":{"line":23,"column":22}},{"generated":{"line":42,"column":26},"source":"node.js","original":{"line":23,"column":14}},{"name":"parseInt","generated":{"line":42,"column":29},"source":"node.js","original":{"line":23,"column":29}},{"name":"dataset","generated":{"line":42,"column":38},"source":"node.js","original":{"line":23,"column":38}},{"name":"hold","generated":{"line":42,"column":46},"source":"node.js","original":{"line":23,"column":46}},{"generated":{"line":42,"column":50},"source":"node.js","original":{"line":23,"column":29}},{"generated":{"line":42,"column":52},"source":"node.js","original":{"line":23,"column":52}},{"generated":{"line":42,"column":54},"source":"node.js","original":{"line":23,"column":29}},{"generated":{"line":42,"column":55},"source":"node.js","original":{"line":23,"column":14}},{"generated":{"line":42,"column":58},"source":"node.js","original":{"line":23,"column":58}},{"generated":{"line":42,"column":59},"source":"node.js","original":{"line":17,"column":11}},{"name":"scale","generated":{"line":43,"column":0},"source":"node.js","original":{"line":24,"column":8}},{"name":"dataset","generated":{"line":43,"column":15},"source":"node.js","original":{"line":24,"column":15}},{"name":"scale","generated":{"line":43,"column":23},"source":"node.js","original":{"line":24,"column":23}},{"generated":{"line":43,"column":28},"source":"node.js","original":{"line":24,"column":15}},{"name":"dataset","generated":{"line":43,"column":31},"source":"node.js","original":{"line":24,"column":31}},{"name":"scale","generated":{"line":43,"column":39},"source":"node.js","original":{"line":24,"column":39}},{"generated":{"line":43,"column":44},"source":"node.js","original":{"line":24,"column":15}},{"generated":{"line":43,"column":47},"source":"node.js","original":{"line":24,"column":47}},{"generated":{"line":43,"column":51},"source":"node.js","original":{"line":17,"column":11}},{"name":"await","generated":{"line":44,"column":0},"source":"node.js","original":{"line":25,"column":8}},{"name":"dataset","generated":{"line":44,"column":15},"source":"node.js","original":{"line":25,"column":15}},{"name":"await","generated":{"line":44,"column":23},"source":"node.js","original":{"line":25,"column":23}},{"generated":{"line":44,"column":28},"source":"node.js","original":{"line":25,"column":15}},{"name":"dataset","generated":{"line":44,"column":31},"source":"node.js","original":{"line":25,"column":31}},{"name":"await","generated":{"line":44,"column":39},"source":"node.js","original":{"line":25,"column":39}},{"generated":{"line":44,"column":44},"source":"node.js","original":{"line":25,"column":15}},{"generated":{"line":44,"column":47},"source":"node.js","original":{"line":25,"column":47}},{"generated":{"line":44,"column":51},"source":"node.js","original":{"line":17,"column":11}},{"generated":{"line":45,"column":0},"source":"node.js","original":{"line":26,"column":8}},{"name":"dataset","generated":{"line":45,"column":20},"source":"node.js","original":{"line":26,"column":20}},{"name":"continue","generated":{"line":45,"column":28},"source":"node.js","original":{"line":26,"column":28}},{"generated":{"line":45,"column":36},"source":"node.js","original":{"line":26,"column":20}},{"generated":{"line":45,"column":41},"source":"node.js","original":{"line":26,"column":41}},{"generated":{"line":45,"column":47},"source":"node.js","original":{"line":17,"column":11}},{"name":"origin","generated":{"line":46,"column":0},"source":"node.js","original":{"line":27,"column":8}},{"name":"dataset","generated":{"line":46,"column":16},"source":"node.js","original":{"line":27,"column":16}},{"name":"origin","generated":{"line":46,"column":24},"source":"node.js","original":{"line":27,"column":24}},{"generated":{"line":46,"column":30},"source":"node.js","original":{"line":27,"column":16}},{"name":"dataset","generated":{"line":46,"column":33},"source":"node.js","original":{"line":27,"column":33}},{"name":"origin","generated":{"line":46,"column":41},"source":"node.js","original":{"line":27,"column":41}},{"generated":{"line":46,"column":47},"source":"node.js","original":{"line":27,"column":16}},{"generated":{"line":46,"column":50},"source":"node.js","original":{"line":27,"column":50}},{"generated":{"line":46,"column":58},"source":"node.js","original":{"line":17,"column":11}},{"name":"offset","generated":{"line":47,"column":0},"source":"node.js","original":{"line":28,"column":8}},{"name":"dataset","generated":{"line":47,"column":16},"source":"node.js","original":{"line":28,"column":16}},{"name":"up","generated":{"line":47,"column":24},"source":"node.js","original":{"line":28,"column":24}},{"generated":{"line":47,"column":26},"source":"node.js","original":{"line":28,"column":16}},{"name":"dataset","generated":{"line":47,"column":30},"source":"node.js","original":{"line":28,"column":30}},{"name":"down","generated":{"line":47,"column":38},"source":"node.js","original":{"line":28,"column":38}},{"generated":{"line":47,"column":42},"source":"node.js","original":{"line":28,"column":16}},{"name":"dataset","generated":{"line":47,"column":46},"source":"node.js","original":{"line":28,"column":46}},{"name":"left","generated":{"line":47,"column":54},"source":"node.js","original":{"line":28,"column":54}},{"generated":{"line":47,"column":58},"source":"node.js","original":{"line":28,"column":16}},{"name":"dataset","generated":{"line":47,"column":62},"source":"node.js","original":{"line":28,"column":62}},{"name":"right","generated":{"line":47,"column":70},"source":"node.js","original":{"line":28,"column":70}},{"generated":{"line":47,"column":75},"source":"node.js","original":{"line":28,"column":16}},{"name":"dataset","generated":{"line":47,"column":78},"source":"node.js","original":{"line":29,"column":14}},{"name":"up","generated":{"line":47,"column":86},"source":"node.js","original":{"line":29,"column":22}},{"generated":{"line":47,"column":88},"source":"node.js","original":{"line":29,"column":14}},{"name":"dataset","generated":{"line":47,"column":92},"source":"node.js","original":{"line":29,"column":28}},{"name":"down","generated":{"line":47,"column":100},"source":"node.js","original":{"line":29,"column":36}},{"generated":{"line":47,"column":104},"source":"node.js","original":{"line":29,"column":14}},{"name":"dataset","generated":{"line":47,"column":108},"source":"node.js","original":{"line":29,"column":44}},{"name":"left","generated":{"line":47,"column":116},"source":"node.js","original":{"line":29,"column":52}},{"generated":{"line":47,"column":120},"source":"node.js","original":{"line":29,"column":14}},{"name":"dataset","generated":{"line":47,"column":124},"source":"node.js","original":{"line":29,"column":60}},{"name":"right","generated":{"line":47,"column":132},"source":"node.js","original":{"line":29,"column":68}},{"generated":{"line":47,"column":137},"source":"node.js","original":{"line":28,"column":16}},{"generated":{"line":47,"column":140},"source":"node.js","original":{"line":30,"column":14}},{"generated":{"line":48,"column":0},"source":"node.js","original":{"line":17,"column":11}},{"generated":{"line":48,"column":5},"source":"node.js","original":{"line":17,"column":4}},{"generated":{"line":49,"column":0},"source":"node.js","original":{"line":32,"column":1}},{"generated":{"line":49,"column":1},"source":"node.js","original":{"line":16,"column":0}},{"name":"HoneyNode","generated":{"line":51,"column":4},"source":"node.js","original":{"line":34,"column":21}},{"generated":{"line":52,"column":0},"source":"node.js","original":{"line":35,"column":4}},{"name":"node","generated":{"line":52,"column":23},"source":"node.js","original":{"line":35,"column":16}},{"generated":{"line":52,"column":27},"source":"node.js","original":{"line":35,"column":4}},{"generated":{"line":52,"column":29},"source":"node.js","original":{"line":35,"column":22}},{"generated":{"line":53,"column":0},"source":"node.js","original":{"line":35,"column":22}},{"name":"node","generated":{"line":55,"column":0},"source":"node.js","original":{"line":36,"column":8}},{"name":"style","generated":{"line":55,"column":13},"source":"node.js","original":{"line":36,"column":13}},{"generated":{"line":55,"column":18},"source":"node.js","original":{"line":36,"column":8}},{"name":"opacity","generated":{"line":55,"column":19},"source":"node.js","original":{"line":36,"column":19}},{"generated":{"line":55,"column":26},"source":"node.js","original":{"line":36,"column":8}},{"generated":{"line":55,"column":29},"source":"node.js","original":{"line":36,"column":29}},{"generated":{"line":55,"column":30},"source":"node.js","original":{"line":36,"column":8}},{"generated":{"line":56,"column":0},"source":"node.js","original":{"line":37,"column":8}},{"name":"node","generated":{"line":56,"column":13},"source":"node.js","original":{"line":37,"column":13}},{"generated":{"line":56,"column":17},"source":"node.js","original":{"line":37,"column":8}},{"name":"node","generated":{"line":56,"column":20},"source":"node.js","original":{"line":37,"column":20}},{"generated":{"line":56,"column":24},"source":"node.js","original":{"line":37,"column":8}},{"generated":{"line":57,"column":0},"source":"node.js","original":{"line":38,"column":8}},{"name":"setParameters","generated":{"line":57,"column":13},"source":"node.js","original":{"line":38,"column":13}},{"generated":{"line":57,"column":26},"source":"node.js","original":{"line":38,"column":8}},{"name":"node","generated":{"line":57,"column":27},"source":"node.js","original":{"line":38,"column":27}},{"name":"dataset","generated":{"line":57,"column":32},"source":"node.js","original":{"line":38,"column":32}},{"generated":{"line":57,"column":39},"source":"node.js","original":{"line":38,"column":8}},{"generated":{"line":58,"column":0},"source":"node.js","original":{"line":39,"column":5}},{"name":"parameters","generated":{"line":62,"column":38},"source":"node.js","original":{"line":40,"column":18}},{"generated":{"line":62,"column":50},"source":"node.js","original":{"line":40,"column":30}},{"generated":{"line":63,"column":0},"source":"node.js","original":{"line":41,"column":8}},{"name":"parameters","generated":{"line":63,"column":17},"source":"node.js","original":{"line":41,"column":13}},{"generated":{"line":63,"column":27},"source":"node.js","original":{"line":41,"column":8}},{"name":"parseParameters","generated":{"line":63,"column":30},"source":"node.js","original":{"line":41,"column":26}},{"name":"parameters","generated":{"line":63,"column":46},"source":"node.js","original":{"line":41,"column":42}},{"generated":{"line":63,"column":56},"source":"node.js","original":{"line":41,"column":26}},{"generated":{"line":63,"column":57},"source":"node.js","original":{"line":41,"column":8}},{"generated":{"line":64,"column":0},"source":"node.js","original":{"line":42,"column":8}},{"name":"effect","generated":{"line":64,"column":17},"source":"node.js","original":{"line":42,"column":13}},{"generated":{"line":64,"column":23},"source":"node.js","original":{"line":42,"column":8}},{"generated":{"line":64,"column":26},"source":"node.js","original":{"line":42,"column":22}},{"generated":{"line":64,"column":56},"source":"node.js","original":{"line":42,"column":37}},{"name":"parameters","generated":{"line":64,"column":61},"source":"node.js","original":{"line":42,"column":42}},{"generated":{"line":64,"column":71},"source":"node.js","original":{"line":42,"column":22}},{"generated":{"line":64,"column":72},"source":"node.js","original":{"line":42,"column":8}},{"generated":{"line":65,"column":0},"source":"node.js","original":{"line":43,"column":5}},{"name":"effect","generated":{"line":69,"column":96},"source":"node.js","original":{"line":44,"column":22}},{"name":"count","generated":{"line":77,"column":0},"source":"node.js","original":{"line":45,"column":12}},{"generated":{"line":77,"column":40},"source":"node.js","original":{"line":45,"column":20}},{"name":"Object","generated":{"line":79,"column":0},"source":"node.js","original":{"line":46,"column":8}},{"name":"keys","generated":{"line":79,"column":39},"source":"node.js","original":{"line":46,"column":15}},{"generated":{"line":79,"column":43},"source":"node.js","original":{"line":46,"column":8}},{"name":"effect","generated":{"line":79,"column":44},"source":"node.js","original":{"line":46,"column":20}},{"generated":{"line":79,"column":50},"source":"node.js","original":{"line":46,"column":8}},{"name":"forEach","generated":{"line":79,"column":52},"source":"node.js","original":{"line":46,"column":28}},{"generated":{"line":79,"column":59},"source":"node.js","original":{"line":46,"column":8}},{"generated":{"line":79,"column":60},"source":"node.js","original":{"line":46,"column":36}},{"name":"key","generated":{"line":79,"column":70},"source":"node.js","original":{"line":46,"column":37}},{"generated":{"line":79,"column":73},"source":"node.js","original":{"line":46,"column":36}},{"generated":{"line":79,"column":75},"source":"node.js","original":{"line":46,"column":45}},{"generated":{"line":80,"column":0},"source":"node.js","original":{"line":47,"column":12}},{"name":"node","generated":{"line":80,"column":42},"source":"node.js","original":{"line":47,"column":17}},{"generated":{"line":80,"column":46},"source":"node.js","original":{"line":47,"column":12}},{"name":"style","generated":{"line":80,"column":47},"source":"node.js","original":{"line":47,"column":22}},{"generated":{"line":80,"column":52},"source":"node.js","original":{"line":47,"column":12}},{"name":"key","generated":{"line":80,"column":53},"source":"node.js","original":{"line":47,"column":28}},{"generated":{"line":80,"column":56},"source":"node.js","original":{"line":47,"column":12}},{"name":"effect","generated":{"line":80,"column":60},"source":"node.js","original":{"line":47,"column":35}},{"name":"key","generated":{"line":80,"column":67},"source":"node.js","original":{"line":47,"column":42}},{"generated":{"line":80,"column":70},"source":"node.js","original":{"line":47,"column":35}},{"generated":{"line":80,"column":71},"source":"node.js","original":{"line":47,"column":12}},{"name":"count","generated":{"line":81,"column":0},"source":"node.js","original":{"line":48,"column":12}},{"generated":{"line":82,"column":0},"source":"node.js","original":{"line":49,"column":9}},{"generated":{"line":82,"column":33},"source":"node.js","original":{"line":46,"column":8}},{"name":"count","generated":{"line":83,"column":65},"source":"node.js","original":{"line":50,"column":15}},{"generated":{"line":109,"column":66},"source":"node.js","original":{"line":53,"column":15}},{"name":"Promise","generated":{"line":109,"column":70},"source":"node.js","original":{"line":53,"column":19}},{"generated":{"line":109,"column":77},"source":"node.js","original":{"line":53,"column":15}},{"generated":{"line":109,"column":78},"source":"node.js","original":{"line":53,"column":27}},{"name":"resolve","generated":{"line":109,"column":88},"source":"node.js","original":{"line":53,"column":28}},{"generated":{"line":109,"column":95},"source":"node.js","original":{"line":53,"column":27}},{"generated":{"line":109,"column":97},"source":"node.js","original":{"line":53,"column":40}},{"generated":{"line":110,"column":0},"source":"node.js","original":{"line":54,"column":12}},{"generated":{"line":110,"column":56},"source":"node.js","original":{"line":54,"column":23}},{"name":"node","generated":{"line":110,"column":63},"source":"node.js","original":{"line":54,"column":28}},{"generated":{"line":110,"column":67},"source":"node.js","original":{"line":54,"column":12}},{"name":"then","generated":{"line":110,"column":69},"source":"node.js","original":{"line":54,"column":34}},{"generated":{"line":110,"column":73},"source":"node.js","original":{"line":54,"column":12}},{"generated":{"line":110,"column":74},"source":"node.js","original":{"line":54,"column":39}},{"generated":{"line":111,"column":0},"source":"node.js","original":{"line":54,"column":39}},{"name":"setTimeout","generated":{"line":111,"column":47},"source":"node.js","original":{"line":54,"column":45}},{"generated":{"line":111,"column":58},"source":"node.js","original":{"line":54,"column":56}},{"generated":{"line":112,"column":0},"source":"node.js","original":{"line":54,"column":56}},{"name":"resolve","generated":{"line":112,"column":51},"source":"node.js","original":{"line":54,"column":62}},{"generated":{"line":112,"column":60},"source":"node.js","original":{"line":54,"column":56}},{"generated":{"line":113,"column":0},"source":"node.js","original":{"line":54,"column":56}},{"generated":{"line":113,"column":41},"source":"node.js","original":{"line":54,"column":45}},{"generated":{"line":113,"column":43},"source":"node.js","original":{"line":54,"column":73}},{"name":"parameters","generated":{"line":113,"column":50},"source":"node.js","original":{"line":54,"column":78}},{"generated":{"line":113,"column":60},"source":"node.js","original":{"line":54,"column":73}},{"name":"hold","generated":{"line":113,"column":61},"source":"node.js","original":{"line":54,"column":89}},{"generated":{"line":113,"column":65},"source":"node.js","original":{"line":54,"column":45}},{"generated":{"line":113,"column":66},"source":"node.js","original":{"line":54,"column":39}},{"generated":{"line":114,"column":0},"source":"node.js","original":{"line":54,"column":39}},{"generated":{"line":114,"column":37},"source":"node.js","original":{"line":54,"column":12}},{"generated":{"line":115,"column":0},"source":"node.js","original":{"line":55,"column":9}},{"generated":{"line":115,"column":33},"source":"node.js","original":{"line":53,"column":15}},{"generated":{"line":133,"column":34},"source":"node.js","original":{"line":57,"column":34}},{"generated":{"line":134,"column":0},"source":"node.js","original":{"line":57,"column":34}},{"generated":{"line":136,"column":0},"source":"node.js","original":{"line":57,"column":34}},{"name":"effect","generated":{"line":136,"column":16},"source":"node.js","original":{"line":57,"column":12}},{"generated":{"line":136,"column":22},"source":"node.js","original":{"line":57,"column":34}},{"generated":{"line":136,"column":93},"source":"node.js","original":{"line":57,"column":21}},{"name":"effect","generated":{"line":136,"column":98},"source":"node.js","original":{"line":57,"column":26}},{"generated":{"line":136,"column":104},"source":"node.js","original":{"line":57,"column":34}},{"generated":{"line":138,"column":0},"source":"node.js","original":{"line":58,"column":8}},{"name":"applyEffect","generated":{"line":138,"column":17},"source":"node.js","original":{"line":58,"column":13}},{"generated":{"line":138,"column":28},"source":"node.js","original":{"line":58,"column":8}},{"name":"effect","generated":{"line":138,"column":29},"source":"node.js","original":{"line":58,"column":25}},{"generated":{"line":138,"column":35},"source":"node.js","original":{"line":58,"column":8}},{"name":"then","generated":{"line":138,"column":37},"source":"node.js","original":{"line":58,"column":33}},{"generated":{"line":138,"column":41},"source":"node.js","original":{"line":58,"column":8}},{"generated":{"line":138,"column":42},"source":"node.js","original":{"line":58,"column":38}},{"generated":{"line":138,"column":54},"source":"node.js","original":{"line":58,"column":44}},{"generated":{"line":139,"column":0},"source":"node.js","original":{"line":59,"column":12}},{"name":"isLoaded","generated":{"line":139,"column":23},"source":"node.js","original":{"line":59,"column":17}},{"generated":{"line":139,"column":31},"source":"node.js","original":{"line":59,"column":12}},{"name":"then","generated":{"line":139,"column":34},"source":"node.js","original":{"line":59,"column":28}},{"generated":{"line":139,"column":38},"source":"node.js","original":{"line":59,"column":12}},{"generated":{"line":139,"column":39},"source":"node.js","original":{"line":59,"column":33}},{"generated":{"line":139,"column":51},"source":"node.js","original":{"line":59,"column":39}},{"name":"setTimeout","generated":{"line":140,"column":0},"source":"node.js","original":{"line":60,"column":16}},{"generated":{"line":140,"column":31},"source":"node.js","original":{"line":60,"column":27}},{"generated":{"line":140,"column":43},"source":"node.js","original":{"line":60,"column":33}},{"generated":{"line":141,"column":0},"source":"node.js","original":{"line":61,"column":20}},{"name":"expose","generated":{"line":141,"column":31},"source":"node.js","original":{"line":61,"column":25}},{"generated":{"line":141,"column":37},"source":"node.js","original":{"line":61,"column":20}},{"generated":{"line":142,"column":0},"source":"node.js","original":{"line":62,"column":17}},{"generated":{"line":142,"column":21},"source":"node.js","original":{"line":60,"column":16}},{"generated":{"line":142,"column":23},"source":"node.js","original":{"line":62,"column":19}},{"name":"parameters","generated":{"line":142,"column":30},"source":"node.js","original":{"line":62,"column":24}},{"generated":{"line":142,"column":40},"source":"node.js","original":{"line":62,"column":19}},{"name":"delay","generated":{"line":142,"column":41},"source":"node.js","original":{"line":62,"column":35}},{"generated":{"line":142,"column":46},"source":"node.js","original":{"line":60,"column":16}},{"generated":{"line":143,"column":0},"source":"node.js","original":{"line":63,"column":13}},{"generated":{"line":143,"column":17},"source":"node.js","original":{"line":59,"column":12}},{"generated":{"line":144,"column":0},"source":"node.js","original":{"line":64,"column":9}},{"generated":{"line":144,"column":13},"source":"node.js","original":{"line":58,"column":8}},{"generated":{"line":145,"column":0},"source":"node.js","original":{"line":65,"column":5}},{"generated":{"line":148,"column":33},"source":"node.js","original":{"line":66,"column":13}},{"generated":{"line":149,"column":0},"source":"node.js","original":{"line":67,"column":8}},{"name":"applyEffect","generated":{"line":149,"column":17},"source":"node.js","original":{"line":67,"column":13}},{"generated":{"line":149,"column":28},"source":"node.js","original":{"line":67,"column":8}},{"generated":{"line":149,"column":29},"source":"node.js","original":{"line":67,"column":25}},{"name":"transform","generated":{"line":150,"column":0},"source":"node.js","original":{"line":68,"column":12}},{"generated":{"line":150,"column":27},"source":"node.js","original":{"line":68,"column":23}},{"generated":{"line":150,"column":29},"source":"node.js","original":{"line":67,"column":25}},{"name":"opacity","generated":{"line":151,"column":0},"source":"node.js","original":{"line":69,"column":12}},{"generated":{"line":151,"column":25},"source":"node.js","original":{"line":69,"column":21}},{"generated":{"line":152,"column":0},"source":"node.js","original":{"line":67,"column":25}},{"generated":{"line":152,"column":13},"source":"node.js","original":{"line":67,"column":8}},{"generated":{"line":153,"column":0},"source":"node.js","original":{"line":71,"column":5}},{"name":"HoneyNode","generated":{"line":159,"column":18},"source":"node.js","original":{"line":34,"column":21}}],"sources":{"node.js":"import generateEffect from './generateEffect'\nimport waitImages from './wait'\n\nconst getDirection = (dataset) => {\n    if (dataset.right) {\n        return 2\n    } else if (dataset.down) {\n        return 3\n    } else if (dataset.left) {\n        return 4\n    } else {\n        return 1\n    }\n}\n\nconst parseParameters = (dataset) => {\n    return {\n        direction: getDirection(dataset),\n        duration: dataset.duration ? dataset.duration : 640,\n        effect: dataset.effect ? dataset.effect : 'fade',\n        expose: dataset.expose ? dataset.expose === 'true' : false,\n        delay: dataset.delay ? parseInt(dataset.delay, 10) : 0,\n        hold: dataset.hold ? parseInt(dataset.hold, 10) : 0,\n        scale: dataset.scale ? dataset.scale : 0.87,\n        await: dataset.await ? dataset.await : null,\n        'continue': dataset.continue === 'true',\n        origin: dataset.origin ? dataset.origin : 'bottom',\n        offset: dataset.up || dataset.down || dataset.left || dataset.right\n            ? dataset.up || dataset.down || dataset.left || dataset.right\n            : 32,\n    }\n}\n\nexport default class HoneyNode {\n    constructor(node) {\n        node.style.opacity = 0\n        this.node = node\n        this.setParameters(node.dataset)\n    }\n    setParameters(parameters) {\n        this.parameters = parseParameters(parameters)\n        this.effect = generateEffect(this.parameters)\n    }\n    async applyEffect(effect) {\n        let count = 0\n        Object.keys(effect).forEach((key) => {\n            this.node.style[key] = effect[key]\n            count++\n        })\n        return count\n    }\n    async isLoaded() {\n        return new Promise((resolve) => {\n            waitImages(this.node).then(() => setTimeout(() => resolve(), this.parameters.hold))\n        })\n    }\n    animate(effect = this.effect) {\n        this.applyEffect(effect).then(() => {\n            this.isLoaded().then(() => {\n                setTimeout(() => {\n                    this.expose()\n                }, this.parameters.delay)\n            })\n        })\n    }\n    expose() {\n        this.applyEffect({\n            transform: '',\n            opacity: 1,\n        })\n    }\n}\n"},"lineCount":null}},"hash":"df4a9050b6cb3ab19a697b2df1a1d160","cacheData":{"env":{}},"id":5}